{"meta":{"quiz_id":"20260711-economics","subject_key":"economics","subject":"অর্থনীতি","chapter":"জাতীয় আয়","date":"2026-07-11"},"qs":[{"q":"মোট দেশজ উৎপাদন (GDP) বলতে কী বোঝায়?","o":["একটি নির্দিষ্ট সময়ে একটি দেশের নাগরিকদের দ্বারা উৎপাদিত সমস্ত চূড়ান্ত পণ্য ও সেবার বাজার মূল্য।","একটি নির্দিষ্ট সময়ে একটি দেশের ভৌগোলিক সীমার মধ্যে উৎপাদিত সমস্ত চূড়ান্ত পণ্য ও সেবার বাজার মূল্য।","একটি নির্দিষ্ট সময়ে একটি দেশের নাগরিকদের দ্বারা উৎপাদিত সমস্ত মধ্যবর্তী ও চূড়ান্ত পণ্য ও সেবার বাজার মূল্য।","একটি নির্দিষ্ট সময়ে একটি দেশের ভৌগোলিক সীমার মধ্যে উৎপাদিত সমস্ত মধ্যবর্তী পণ্য ও সেবার বাজার মূল্য।"]},{"q":"মোট জাতীয় উৎপাদন (GNP) গণনা করার সময় নিম্নলিখিত কোনটি GDP-এর সাথে যোগ করা হয়?","o":["বিদেশীদের দ্বারা দেশের অভ্যন্তরে অর্জিত আয়।","দেশের নাগরিকদের দ্বারা বিদেশে অর্জিত আয়।","সরকারি ব্যয়।","অবচয় (Depreciation)।"]},{"q":"নীচের কোনটি 'ফ্যাক্টর কস্টে নিট জাতীয় উৎপাদন' (NNP at Factor Cost) নামেও পরিচিত?","o":["মোট দেশজ উৎপাদন (GDP)","মোট জাতীয় উৎপাদন (GNP)","নিট জাতীয় উৎপাদন (NNP)","জাতীয় আয় (National Income)"]},{"q":"জাতীয় আয় পরিমাপের আয় পদ্ধতির (Income Method) অধীনে নিম্নলিখিত কোনটি অন্তর্ভুক্ত নয়?","o":["মজুরি ও বেতন।","ভাড়া ও সুদ।","নিট রপ্তানি।","লাভ।"]},{"q":"মাথাপিছু আয় (Per Capita Income) কীভাবে গণনা করা হয়?","o":["মোট জাতীয় আয় / মোট জনসংখ্যা।","মোট দেশজ উৎপাদন / মোট জনসংখ্যা।","মোট জাতীয় আয় - মোট জনসংখ্যা।","মোট দেশজ উৎপাদন + মোট জনসংখ্যা।"]},{"q":"নামমাত্র জিডিপি (Nominal GDP) এবং প্রকৃত জিডিপি (Real GDP) এর মধ্যে প্রধান পার্থক্য কী?","o":["নামমাত্র জিডিপি বর্তমান মূল্যে গণনা করা হয়, প্রকৃত জিডিপি স্থির মূল্যে গণনা করা হয়।","নামমাত্র জিডিপি স্থির মূল্যে গণনা করা হয়, প্রকৃত জিডিপি বর্তমান মূল্যে গণনা করা হয়।","নামমাত্র জিডিপি কেবল পণ্য অন্তর্ভুক্ত করে, প্রকৃত জিডিপি পণ্য ও সেবা উভয়ই অন্তর্ভুক্ত করে।","নামমাত্র জিডিপি কেবল সেবা অন্তর্ভুক্ত করে, প্রকৃত জিডিপি পণ্য ও সেবা উভয়ই অন্তর্ভুক্ত করে।"]},{"q":"জাতীয় আয় পরিমাপের ক্ষেত্রে নিম্নলিখিত কোনটি একটি প্রধান সমস্যা?","o":["দ্বৈত গণনা (Double Counting) এড়ানো।","সরকারি ব্যয়ের অপ্রতুল তথ্য।","শুধুমাত্র চূড়ান্ত পণ্য ও সেবা অন্তর্ভুক্ত করা।","কৃষি খাতের সহজলভ্য তথ্য।"]},{"q":"'সবুজ জিডিপি' (Green GDP) বলতে কী বোঝায়?","o":["পরিবেশ দূষণ এবং প্রাকৃতিক সম্পদ হ্রাসের খরচ বাদ দিয়ে গণনা করা জিডিপি।","কৃষি উৎপাদন বৃদ্ধির ফলে অর্জিত জিডিপি।","পরিবেশ বান্ধব শিল্পের দ্বারা উৎপাদিত জিডিপি।","সবুজ শক্তি উৎস ব্যবহার করে উৎপাদিত জিডিপি।"]},{"q":"জাতীয় আয় গণনার ব্যয় পদ্ধতিতে (Expenditure Method) নিম্নলিখিত কোনটি অন্তর্ভুক্ত নয়?","o":["ব্যক্তিগত ভোগ ব্যয় (Private Consumption Expenditure)।","মোট অভ্যন্তরীণ বিনিয়োগ (Gross Domestic Investment)।","সরকারের নিট ঋণ (Net Government Borrowing)।","নিট রপ্তানি (Net Exports)।"]},{"q":"ভারতে প্রথম কে বৈজ্ঞানিক পদ্ধতিতে জাতীয় আয় অনুমান করেছিলেন?","o":["দাদাভাই নওরোজী।","পি. সি. মহলানবিশ।","ভি. কে. আর. ভি. রাও।","জওহরলাল নেহেরু।"]}]}